MANIFEST.in
README.rst
setup.py
salientdetect/__init__.py
salientdetect/color_dist.npy
salientdetect/detector.pyx
salientdetect/mk_dist_mat.py