Metadata-Version: 1.1
Name: salientdetect
Version: 0.0.1
Summary: Slient Region Detector from Image
Home-page: https://github.com/shunsukeaihara/objectdetect
Author: Shunsuke Aihara
Author-email: aihara@argmax.jp
License: MIT License
Platform: UNKNOWN
Classifier: Programming Language :: Python
Classifier: Programming Language :: Python :: 3
Classifier: Programming Language :: Python :: 2
